tech_summary/__init__.py
tech_summary/main.py
tech_summary/prompts.py
tech_summary-2025.12.21234318.dist-info/METADATA
tech_summary-2025.12.21234318.dist-info/WHEEL
tech_summary-2025.12.21234318.dist-info/top_level.txt
tech_summary-2025.12.21234318.dist-info/RECORD
