Metadata-Version: 2.4
Name: tech-summary
Version: 2025.12.21234318
Summary: tech-summary processes text to extract structured summaries of technical concepts, ensuring consistent and reliable output for developers, educators, and writers.
Author-email: tech-summary <hi@eugene.plus>
License: MIT
Project-URL: Homepage, https://github.com/chigwell/tech-summary
Requires-Python: >=3.9
Requires-Dist: langchain-llm7>=0.0.0
Requires-Dist: llmatch-messages>=0.0.0
Requires-Dist: langchain-core>=0.3.0
